basic_stuff/counter_project/rtl/counter.v
`timescale 1ns/1ps

module counter (
    input wire clk,
    input wire rst,
    input wire valid,
    output reg[7:0] count
);

    always @(posedge clk) begin
        if (rst) begin
            count <= 8'd0;
        end else if (valid) begin
            count <= count + 8'd1;
        end
    end

endmodule

basic_stuff/counter_project/tb/counter_tb.v
`timescale 1ns/1ps

module counter_tb;

    reg clk;
    reg rst;
    reg valid;
    wire [7:0] count;

    counter uut (
        .clk(clk),
        .rst(rst),
        .valid(valid),
        .count(count)
    );

    always #5 clk = ~clk;

    initial begin
        // dump waveforms
        $dumpfile("counter.vcd");
        $dumpvars(0, counter_tb);

        // Initialize signals
        clk = 0;
        rst = 0;
        valid = 0;

        // Test reset
        rst = 1;
        #10;
        rst = 0;

        // Test counting
        valid = 1;
        #100;
        valid = 0;
        #100;
        valid = 1;
        #50;

        // Finish simulation
        #10;
        $finish;
    end

endmodule

basic_stuff/counter_project/sim/counter.vcd
$date
	Thu Jan 01 19:37:57 2026
$end
$version
	Icarus Verilog
$end
$timescale
	1ps
$end
$scope module counter_tb $end
$var wire 8 ! count [7:0] $end
$var reg 1 " clk $end
$var reg 1 # rst $end
$var reg 1 $ valid $end
$scope module uut $end
$var wire 1 " clk $end
$var wire 1 # rst $end
$var wire 1 $ valid $end
$var reg 8 % count [7:0] $end
$upscope $end
$upscope $end
$enddefinitions $end
$comment Show the parameter values. $end
$dumpall
$end
#0
$dumpvars
bx %
0$
1#
0"
bx !
$end
#5000
b0 !
b0 %
1"
#10000
0"
1$
0#
#15000
b1 !
b1 %
1"
#20000
0"
#25000
b10 !
b10 %
1"
#30000
0"
#35000
b11 !
b11 %
1"
#40000
0"
#45000
b100 !
b100 %
1"
#50000
0"
#55000
b101 !
b101 %
1"
#60000
0"
#65000
b110 !
b110 %
1"
#70000
0"
#75000
b111 !
b111 %
1"
#80000
0"
#85000
b1000 !
b1000 %
1"
#90000
0"
#95000
b1001 !
b1001 %
1"
#100000
0"
#105000
b1010 !
b1010 %
1"
#110000
0"
0$
#115000
1"
#120000
0"
#125000
1"
#130000
0"
#135000
1"
#140000
0"
#145000
1"
#150000
0"
#155000
1"
#160000
0"
#165000
1"
#170000
0"
#175000
1"
#180000
0"
#185000
1"
#190000
0"
#195000
1"
#200000
0"
#205000
1"
#210000
0"
1$
#215000
b1011 !
b1011 %
1"
#220000
0"
#225000
b1100 !
b1100 %
1"
#230000
0"
#235000
b1101 !
b1101 %
1"
#240000
0"
#245000
b1110 !
b1110 %
1"
#250000
0"
#255000
b1111 !
b1111 %
1"
#260000
0"
#265000
b10000 !
b10000 %
1"
