basic_stuff/pulse_generator_project/rtl/pulse_generator.v
`timescale 1ns/1ps

// goal: write a pulse generator that generates a pulse of width 1 cycle every N cycles

module pulse_generator (
    input wire clk,
    input wire rst,
    output reg pulse,
    output reg[7:0] clk_count,
    output reg[7:0] pulse_count
);

    // parameter to set the pulse interval
    parameter N = 10;

    // main logic
    always @(posedge clk) begin
        pulse <= 0;
        if (rst) begin
            clk_count <= 0;
            pulse_count <= 0;
            pulse <= 0;
        end else begin
            if (clk_count == N - 1) begin
                pulse <= 1;
                pulse_count <= pulse_count + 1;
                clk_count <= 0;
            end else begin
                pulse <= 0;
                clk_count <= clk_count + 1;
            end
        end
    end 

endmodule

basic_stuff/pulse_generator_project/tb/pulse_generator_tb.v
`timescale 1ns/1ps

module pulse_generator_tb;

    reg clk;
    reg rst;
    wire pulse;
    wire [7:0] clk_count;
    wire [7:0] pulse_count;

    pulse_generator uut (
        .clk(clk),
        .rst(rst),
        .pulse(pulse),
        .clk_count(clk_count),
        .pulse_count(pulse_count)
    );

    always #5 clk = ~clk;

    initial begin
        // dump waveforms
        $dumpfile("pulse_generator.vcd");
        $dumpvars(0, pulse_generator_tb);

        // apply test vectors
        clk = 0;
        rst = 0;

        // Test reset
        rst = 1;
        #10;
        rst = 0;

        // Run for a number of clock cycles to observe pulse generation
        #392
        // Test reset
        rst = 1;
        #37;
        rst = 0;
        #550;

        // Finish simulation
        $finish;
    end

endmodule

basic_stuff/pulse_generator_project/sim/pulse_generator.vcd
$date
	Thu Jan 01 20:34:51 2026
$end
$version
	Icarus Verilog
$end
$timescale
	1ps
$end
$scope module pulse_generator_tb $end
$var wire 8 ! pulse_count [7:0] $end
$var wire 1 " pulse $end
$var wire 8 # clk_count [7:0] $end
$var reg 1 $ clk $end
$var reg 1 % rst $end
$scope module uut $end
$var wire 1 $ clk $end
$var wire 1 % rst $end
$var parameter 32 & N $end
$var reg 8 ' clk_count [7:0] $end
$var reg 1 " pulse $end
$var reg 8 ( pulse_count [7:0] $end
$upscope $end
$upscope $end
$enddefinitions $end
$comment Show the parameter values. $end
$dumpall
b1010 &
$end
#0
$dumpvars
bx (
bx '
1%
0$
bx #
x"
bx !
$end
#5000
b0 !
b0 (
b0 #
b0 '
0"
1$
#10000
0$
0%
#15000
b1 #
b1 '
1$
#20000
0$
#25000
b10 #
b10 '
1$
#30000
0$
#35000
b11 #
b11 '
1$
#40000
0$
#45000
b100 #
b100 '
1$
#50000
0$
#55000
b101 #
b101 '
1$
#60000
0$
#65000
b110 #
b110 '
1$
#70000
0$
#75000
b111 #
b111 '
1$
#80000
0$
#85000
b1000 #
b1000 '
1$
#90000
0$
#95000
b1001 #
b1001 '
1$
#100000
0$
#105000
b0 #
b0 '
b1 !
b1 (
1"
1$
#110000
0$
#115000
b1 #
b1 '
0"
1$
#120000
0$
#125000
b10 #
b10 '
1$
#130000
0$
#135000
b11 #
b11 '
1$
#140000
0$
#145000
b100 #
b100 '
1$
#150000
0$
#155000
b101 #
b101 '
1$
#160000
0$
#165000
b110 #
b110 '
1$
#170000
0$
#175000
b111 #
b111 '
1$
#180000
0$
#185000
b1000 #
b1000 '
1$
#190000
0$
#195000
b1001 #
b1001 '
1$
#200000
0$
#205000
b0 #
b0 '
b10 !
b10 (
1"
1$
#210000
0$
#215000
b1 #
b1 '
0"
1$
#220000
0$
#225000
b10 #
b10 '
1$
#230000
0$
#235000
b11 #
b11 '
1$
#240000
0$
#245000
b100 #
b100 '
1$
#250000
0$
#255000
b101 #
b101 '
1$
#260000
0$
#265000
b110 #
b110 '
1$
#270000
0$
#275000
b111 #
b111 '
1$
#280000
0$
#285000
b1000 #
b1000 '
1$
#290000
0$
#295000
b1001 #
b1001 '
1$
#300000
0$
#305000
b0 #
b0 '
b11 !
b11 (
1"
1$
#310000
0$
#315000
b1 #
b1 '
0"
1$
#320000
0$
#325000
b10 #
b10 '
1$
#330000
0$
#335000
b11 #
b11 '
1$
#340000
0$
#345000
b100 #
b100 '
1$
#350000
0$
#355000
b101 #
b101 '
1$
#360000
0$
#365000
b110 #
b110 '
1$
#370000
0$
#375000
b111 #
b111 '
1$
#380000
0$
#385000
b1000 #
b1000 '
1$
#390000
0$
#395000
b1001 #
b1001 '
1$
#400000
0$
#402000
1%
#405000
b0 !
b0 (
b0 #
b0 '
1$
#410000
0$
#415000
1$
#420000
0$
#425000
1$
#430000
0$
#435000
1$
#439000
0%
#440000
0$
#445000
b1 #
b1 '
1$
#450000
0$
#455000
b10 #
b10 '
1$
#460000
0$
#465000
b11 #
b11 '
1$
#470000
0$
#475000
b100 #
b100 '
1$
#480000
0$
#485000
b101 #
b101 '
1$
#490000
0$
#495000
b110 #
b110 '
1$
#500000
0$
#505000
b111 #
b111 '
1$
#510000
0$
#515000
b1000 #
b1000 '
1$
#520000
0$
#525000
b1001 #
b1001 '
1$
#530000
0$
#535000
b0 #
b0 '
b1 !
b1 (
1"
1$
#540000
0$
#545000
b1 #
b1 '
0"
1$
#550000
0$
#555000
b10 #
b10 '
1$
#560000
0$
#565000
b11 #
b11 '
1$
#570000
0$
#575000
b100 #
b100 '
1$
#580000
0$
#585000
b101 #
b101 '
1$
#590000
0$
#595000
b110 #
b110 '
1$
#600000
0$
#605000
b111 #
b111 '
1$
#610000
0$
#615000
b1000 #
b1000 '
1$
#620000
0$
#625000
b1001 #
b1001 '
1$
#630000
0$
#635000
b0 #
b0 '
b10 !
b10 (
1"
1$
#640000
0$
#645000
b1 #
b1 '
0"
1$
#650000
0$
#655000
b10 #
b10 '
1$
#660000
0$
#665000
b11 #
b11 '
1$
#670000
0$
#675000
b100 #
b100 '
1$
#680000
0$
#685000
b101 #
b101 '
1$
#690000
0$
#695000
b110 #
b110 '
1$
#700000
0$
#705000
b111 #
b111 '
1$
#710000
0$
#715000
b1000 #
b1000 '
1$
#720000
0$
#725000
b1001 #
b1001 '
1$
#730000
0$
#735000
b0 #
b0 '
b11 !
b11 (
1"
1$
#740000
0$
#745000
b1 #
b1 '
0"
1$
#750000
0$
#755000
b10 #
b10 '
1$
#760000
0$
#765000
b11 #
b11 '
1$
#770000
0$
#775000
b100 #
b100 '
1$
#780000
0$
#785000
b101 #
b101 '
1$
#790000
0$
#795000
b110 #
b110 '
1$
#800000
0$
#805000
b111 #
b111 '
1$
#810000
0$
#815000
b1000 #
b1000 '
1$
#820000
0$
#825000
b1001 #
b1001 '
1$
#830000
0$
#835000
b0 #
b0 '
b100 !
b100 (
1"
1$
#840000
0$
#845000
b1 #
b1 '
0"
1$
#850000
0$
#855000
b10 #
b10 '
1$
#860000
0$
#865000
b11 #
b11 '
1$
#870000
0$
#875000
b100 #
b100 '
1$
#880000
0$
#885000
b101 #
b101 '
1$
#890000
0$
#895000
b110 #
b110 '
1$
#900000
0$
#905000
b111 #
b111 '
1$
#910000
0$
#915000
b1000 #
b1000 '
1$
#920000
0$
#925000
b1001 #
b1001 '
1$
#930000
0$
#935000
b0 #
b0 '
b101 !
b101 (
1"
1$
#940000
0$
#945000
b1 #
b1 '
0"
1$
#950000
0$
#955000
b10 #
b10 '
1$
#960000
0$
#965000
b11 #
b11 '
1$
#970000
0$
#975000
b100 #
b100 '
1$
#980000
0$
#985000
b101 #
b101 '
1$
