basic_stuff/edge_detector_project/rtl/edge_detector.v
`timescale 1ns/1ps

module edge_detector (
    input wire clk,
    input wire rst,
    input wire in,
    output reg edge_pulse
);

    reg[1:0] input_history;

    always @(posedge clk) begin
        input_history = {input_history[0], in};
        if (rst) begin
            edge_pulse <= 0;
            input_history[0] <= in;
            input_history[1] <= in;
        end else begin
            if (input_history == 2'b01) begin
                edge_pulse <= 1;
            end else if (input_history == 2'b10) begin
                edge_pulse <= 0;
            end else begin
                edge_pulse <= 0;
            end
        end
    end
endmodule

basic_stuff/edge_detector_project/tb/edge_detector_tb.v
`timescale 1ns/1ps

module edge_detector_tb;

    reg clk;
    reg rst;
    reg in; 
    wire edge_pulse;

    edge_detector uut (
        .clk(clk),
        .rst(rst),
        .in(in),
        .edge_pulse(edge_pulse)
    );

    always #5 clk = ~clk;

    initial begin
        // dump waveforms
        $dumpfile("edge_detector.vcd");
        $dumpvars(0, edge_detector_tb);

        // Initialize signals
        clk = 0;
        rst = 0;
        in = 0;

        // Test reset
        rst = 1;
        #30;
        rst = 0;

        // Test edge detection
        #100;
        in = 1;
        #80;
        in = 0;
        #60;
        in = 1;
        #40;
        in = 0;
        #50; 
        in = 1;
        #30;
        in = 0;
        #10;
        in = 1;
        #10;
        in = 0;
        #1000;
        in = 1;
        #20;
        in = 0;

        // Finish simulation
        #20;
        $finish;
    end
endmodule

basic_stuff/edge_detector_project/sim/edge_detector.vcd
$date
	Thu Jan 01 21:52:51 2026
$end
$version
	Icarus Verilog
$end
$timescale
	1ps
$end
$scope module edge_detector_tb $end
$var wire 1 ! edge_pulse $end
$var reg 1 " clk $end
$var reg 1 # in $end
$var reg 1 $ rst $end
$scope module uut $end
$var wire 1 " clk $end
$var wire 1 # in $end
$var wire 1 $ rst $end
$var reg 1 ! edge_pulse $end
$var reg 2 % input_history [1:0] $end
$upscope $end
$upscope $end
$enddefinitions $end
$comment Show the parameter values. $end
$dumpall
$end
#0
$dumpvars
bx %
1$
0#
0"
x!
$end
#5000
0!
b0 %
1"
#10000
0"
#15000
1"
#20000
0"
#25000
1"
#30000
0"
0$
#35000
1"
#40000
0"
#45000
1"
#50000
0"
#55000
1"
#60000
0"
#65000
1"
#70000
0"
#75000
1"
#80000
0"
#85000
1"
#90000
0"
#95000
1"
#100000
0"
#105000
1"
#110000
0"
#115000
1"
#120000
0"
#125000
1"
#130000
0"
1#
#135000
1!
b1 %
1"
#140000
0"
#145000
0!
b11 %
1"
#150000
0"
#155000
1"
#160000
0"
#165000
1"
#170000
0"
#175000
1"
#180000
0"
#185000
1"
#190000
0"
#195000
1"
#200000
0"
#205000
1"
#210000
0"
0#
#215000
b10 %
1"
#220000
0"
#225000
b0 %
1"
#230000
0"
#235000
1"
#240000
0"
#245000
1"
#250000
0"
#255000
1"
#260000
0"
#265000
1"
#270000
0"
1#
#275000
1!
b1 %
1"
#280000
0"
#285000
0!
b11 %
1"
#290000
0"
#295000
1"
#300000
0"
#305000
1"
#310000
0"
0#
#315000
b10 %
1"
#320000
0"
#325000
b0 %
1"
#330000
0"
#335000
1"
#340000
0"
#345000
1"
#350000
0"
#355000
1"
#360000
0"
1#
#365000
1!
b1 %
1"
#370000
0"
#375000
0!
b11 %
1"
#380000
0"
#385000
1"
#390000
0"
0#
#395000
b10 %
1"
#400000
0"
1#
#405000
1!
b1 %
1"
#410000
0"
0#
#415000
0!
b10 %
1"
#420000
0"
#425000
b0 %
1"
